distribution_playground/__info__.py
distribution_playground/__init__.py
distribution_playground/density_maps.py
distribution_playground/distribution_utils.py
distribution_playground/source_distribution.py
distribution_playground/understand_kl_divergence.py
distribution_playground/density_map_imgs/QR_code.png
distribution_playground/density_map_imgs/sprial.png
distribution_playground/density_map_imgs/words.png
distribution_playground-0.1.2.dist-info/METADATA
distribution_playground-0.1.2.dist-info/WHEEL
distribution_playground-0.1.2.dist-info/top_level.txt
distribution_playground-0.1.2.dist-info/RECORD
